image_processing034/__init__.py
image_processing034/combination.py
image_processing034/transformation.py
image_processing034-0.0.1.dist-info/METADATA
image_processing034-0.0.1.dist-info/WHEEL
image_processing034-0.0.1.dist-info/top_level.txt
image_processing034-0.0.1.dist-info/RECORD
