Metadata-Version: 2.1
Name: image_processing034
Version: 0.0.1
Summary: Image processing package using skimage
Home-page: https://github.com/Anne034/image_processing
Author: Edyane Araujo
Requires-Python: >=3.5
Requires-Dist: scikit-image
Requires-Dist: numpy
Requires-Dist: pillow
